ascnumpy/__init__.py
ascnumpy-0.0.1.dist-info/LICENSE
ascnumpy-0.0.1.dist-info/METADATA
ascnumpy-0.0.1.dist-info/WHEEL
ascnumpy-0.0.1.dist-info/top_level.txt
ascnumpy-0.0.1.dist-info/RECORD
