Metadata-Version: 2.1
Name: ascnumpy
Version: 0.0.1
Summary: An empty Python package for demonstration.
Home-page: https://gitcode.com/cann/ascnumpy
Author: CANN
Author-email: cann@cann.team
Classifier: Programming Language :: Python :: 3
Classifier: Operating System :: OS Independent
Requires-Python: >=3.6
License-File: LICENSE
